slurmflow/__init__.py
slurmflow/config.py
slurmflow/driver.py
slurmflow/serializer.py
slurm_workflow-0.22.dist-info/METADATA
slurm_workflow-0.22.dist-info/WHEEL
slurm_workflow-0.22.dist-info/top_level.txt
slurm_workflow-0.22.dist-info/RECORD
