Metadata-Version: 2.1
Name: slurm-workflow
Version: 0.22
Summary: A Python module for running workflows on a Slurm cluster.
Author: Lukas
Author-email: lherron@umd.edu
Classifier: Programming Language :: Python :: 3
Classifier: License :: OSI Approved :: MIT License
Classifier: Operating System :: OS Independent
Requires-Dist: numpy
Requires-Dist: h5py
Requires-Dist: blosc2
Requires-Dist: dill
Requires-Dist: pyyaml
